COPYING
COPYING.lesser
MANIFEST.in
NOTICE
README.md
requirements.txt
setup.py
KeralaPyApiV2.egg-info/PKG-INFO
KeralaPyApiV2.egg-info/SOURCES.txt
KeralaPyApiV2.egg-info/dependency_links.txt
KeralaPyApiV2.egg-info/not-zip-safe
KeralaPyApiV2.egg-info/requires.txt
KeralaPyApiV2.egg-info/top_level.txt
compiler/__init__.py
compiler/api/__init__.py
compiler/api/compiler.py
compiler/api/source/auth_key.tl
compiler/api/source/main_api.tl
compiler/api/source/sys_msgs.tl
compiler/api/template/mtproto.txt
compiler/api/template/pyrogram.txt
compiler/docs/__init__.py
compiler/docs/compiler.py
compiler/docs/template/page.txt
compiler/docs/template/toctree.txt
compiler/error/__init__.py
compiler/error/compiler.py
compiler/error/source/303_SEE_OTHER.tsv
compiler/error/source/400_BAD_REQUEST.tsv
compiler/error/source/401_UNAUTHORIZED.tsv
compiler/error/source/403_FORBIDDEN.tsv
compiler/error/source/406_NOT_ACCEPTABLE.tsv
compiler/error/source/420_FLOOD.tsv
compiler/error/source/500_INTERNAL_SERVER_ERROR.tsv
compiler/error/template/class.txt
compiler/error/template/sub_class.txt
pyrogram/__init__.py
pyrogram/api/__init__.py
pyrogram/api/core/__init__.py
pyrogram/api/core/future_salt.py
pyrogram/api/core/future_salts.py
pyrogram/api/core/gzip_packed.py
pyrogram/api/core/list.py
pyrogram/api/core/message.py
pyrogram/api/core/msg_container.py
pyrogram/api/core/tl_object.py
pyrogram/api/core/primitives/__init__.py
pyrogram/api/core/primitives/bool.py
pyrogram/api/core/primitives/bytes.py
pyrogram/api/core/primitives/double.py
pyrogram/api/core/primitives/int.py
pyrogram/api/core/primitives/string.py
pyrogram/api/core/primitives/vector.py
pyrogram/client/__init__.py
pyrogram/client/client.py
pyrogram/client/ext/__init__.py
pyrogram/client/ext/base_client.py
pyrogram/client/ext/dispatcher.py
pyrogram/client/ext/emoji.py
pyrogram/client/ext/file_data.py
pyrogram/client/ext/mime.types
pyrogram/client/ext/syncer.py
pyrogram/client/ext/utils.py
pyrogram/client/filters/__init__.py
pyrogram/client/filters/filter.py
pyrogram/client/filters/filters.py
pyrogram/client/handlers/__init__.py
pyrogram/client/handlers/callback_query_handler.py
pyrogram/client/handlers/deleted_messages_handler.py
