Metadata-Version: 2.1
Name: KeralaPyApiV2
Version: 2.0.2020
Summary: Telegram MTProto API Client Library and Framework for Python
Home-page: https://github.com/KeralaPyApi
Author: Mario
Author-email: KeralaPyApi@gmail.com
License: LGPLv3+
Download-URL: https://github.com/KeralaPyApi/KeralaPyApi/releases/latest
Project-URL: Tracker, https://github.com/pyrogram/pyrogram/issues
Project-URL: Community, https://t.me/Pyrogram
Project-URL: Source, https://github.com/pyrogram/pyrogram
Project-URL: Documentation, https://docs.pyrogram.org
Keywords: telegram chat messenger mtproto api client library python
Platform: UNKNOWN
Classifier: Development Status :: 4 - Beta
Classifier: Intended Audience :: Developers
Classifier: Natural Language :: English
Classifier: License :: OSI Approved :: GNU Lesser General Public License v3 or later (LGPLv3+)
Classifier: Operating System :: OS Independent
Classifier: Programming Language :: Python
Classifier: Programming Language :: Python :: 3
Classifier: Programming Language :: Python :: 3.5
Classifier: Programming Language :: Python :: 3.6
Classifier: Programming Language :: Python :: 3.7
Classifier: Programming Language :: Python :: 3.8
Classifier: Programming Language :: Python :: Implementation
Classifier: Programming Language :: Python :: Implementation :: CPython
Classifier: Programming Language :: Python :: Implementation :: PyPy
Classifier: Topic :: Internet
Classifier: Topic :: Communications
Classifier: Topic :: Communications :: Chat
Classifier: Topic :: Software Development :: Libraries
Classifier: Topic :: Software Development :: Libraries :: Python Modules
Classifier: Topic :: Software Development :: Libraries :: Application Frameworks
Requires-Python: ~=3.5
Provides-Extra: fast
